setup.py
bsetools/__init__.py
bsetools/bsetools.py
bsetools/bsetools_test.py
bsetools/test.py
bsetools.egg-info/PKG-INFO
bsetools.egg-info/SOURCES.txt
bsetools.egg-info/dependency_links.txt
bsetools.egg-info/requires.txt
bsetools.egg-info/top_level.txt