Metadata-Version: 1.0
Name: bsetools
Version: 0.3.2
Summary: Get BSE quotes
Home-page: https://github.com/shahronak47/bsetools
Author: Ronak Shah
Author-email: shahronak47@yahoo.in
License: MIT
Platform: UNKNOWN
